phantomtext/__init__.py
phantomtext/attack_base.py
phantomtext/attack_base_injection.py
phantomtext/content_injection.py
phantomtext/content_obfuscation.py
phantomtext/file_sanitization.py
phantomtext/file_scanning.py
phantomtext/font-poisoning.py
phantomtext/test.py
phantomtext/text_loader.py
phantomtext/text_saver.py
phantomtext/fonts/DejaVuSans.cw127.pkl
phantomtext/fonts/DejaVuSans.pkl
phantomtext/fonts/DejaVuSans.ttf
phantomtext/formats/__init__.py
phantomtext/formats/docx.py
phantomtext/formats/html.py
phantomtext/formats/pdf.py
phantomtext/formats/txt.py
phantomtext/formats/utils.py
phantomtext/injection/camouflage_injection.py
phantomtext/injection/outofbound_injection.py
phantomtext/injection/transparent_injection.py
phantomtext/injection/zerosize_injection.py
phantomtext/obfuscation/diacritical_marks.py
phantomtext/obfuscation/homoglyph_text.py
phantomtext/obfuscation/reordering_char.py
phantomtext/obfuscation/zero_width_text.py
phantomtext/utils/__init__.py
phantomtext/utils/helpers.py
phantomtext-0.1.1.dist-info/licenses/LICENSE
phantomtext-0.1.1.dist-info/METADATA
phantomtext-0.1.1.dist-info/WHEEL
phantomtext-0.1.1.dist-info/top_level.txt
phantomtext-0.1.1.dist-info/RECORD
