Metadata-Version: 2.4
Name: phantomtext
Version: 0.1.1
Summary: A toolkit for content injection, obfuscation, scanning, and sanitization of various document formats. If you use this library, please cite: Castagnaro et al. 'The Hidden Threat in Plain Text: Attacking RAG Data Loaders' (2025).
Home-page: https://github.com/lucapajola/PhantomText
Author: Luca Pajola
Author-email: Luca Pajola <luca.pajola@example.com>
License-Expression: MIT
Project-URL: Homepage, https://github.com/lucapajola/PhantomText
Project-URL: Bug Reports, https://github.com/lucapajola/PhantomText/issues
Project-URL: Source, https://github.com/lucapajola/PhantomText
Keywords: text,obfuscation,steganography,content,injection,document,security
Classifier: Development Status :: 3 - Alpha
Classifier: Intended Audience :: Developers
Classifier: Intended Audience :: Science/Research
Classifier: Topic :: Security
Classifier: Topic :: Text Processing
Classifier: Topic :: Software Development :: Libraries :: Python Modules
Classifier: Programming Language :: Python :: 3
Classifier: Programming Language :: Python :: 3.7
Classifier: Programming Language :: Python :: 3.8
Classifier: Programming Language :: Python :: 3.9
Classifier: Programming Language :: Python :: 3.10
Classifier: Programming Language :: Python :: 3.11
Classifier: Operating System :: OS Independent
Requires-Python: >=3.7
License-File: LICENSE
Requires-Dist: Flask>=2.0.1
Requires-Dist: requests>=2.25.1
Requires-Dist: PyPDF2>=3.0.0
Requires-Dist: python-docx>=0.8.10
Requires-Dist: beautifulsoup4>=4.9.3
Requires-Dist: lxml>=4.6.3
Requires-Dist: pytest>=6.2.4
Requires-Dist: reportlab>=4.2.5
Requires-Dist: numpy>=1.19.0
Requires-Dist: tqdm>=4.60.0
Dynamic: author
Dynamic: home-page
Dynamic: license-file
Dynamic: requires-python
